.DS_Store
pdfmb/__init__.py
pdfmb/merge.py
pdfmb/utils.py
pdfmb-0.0.6.dist-info/LICENSE
pdfmb-0.0.6.dist-info/METADATA
pdfmb-0.0.6.dist-info/WHEEL
pdfmb-0.0.6.dist-info/top_level.txt
pdfmb-0.0.6.dist-info/RECORD
