Metadata-Version: 2.1
Name: pdfmb
Version: 0.0.6
Summary: Merge PDF files with bookmarks
Home-page: https://github.com/1081/pdfmb
License: MIT
Keywords: pdf merge add bookmark bookmarks outline folder pikepdf pdfs nested hierarchy structure
Platform: UNKNOWN
Classifier: License :: OSI Approved :: MIT License
Classifier: Programming Language :: Python :: 3
Classifier: Programming Language :: Python :: 3.10
Requires-Python: >=3
License-File: LICENSE
Requires-Dist: pikepdf
